att_iot_gateway/att_iot_gateway.py
att_iot_gateway/__init__.py
att_iot_gateway-0.1.3.dist-info/DESCRIPTION.rst
att_iot_gateway-0.1.3.dist-info/METADATA
att_iot_gateway-0.1.3.dist-info/metadata.json
att_iot_gateway-0.1.3.dist-info/RECORD
att_iot_gateway-0.1.3.dist-info/top_level.txt
att_iot_gateway-0.1.3.dist-info/WHEEL
