Metadata-Version: 2.0
Name: att-iot-gateway
Version: 0.1.3
Summary: This package provides device & asset management + data feed features for the AllThingsTalk platform to your application.
Home-page: https://github.com/allthingstalk/rpi-python-gateway-client
Author: Jan Bogaerts
Author-email: jb@allthingstalk.com
License: MIT
Platform: UNKNOWN
Requires-Dist: paho-mqtt
